LICENSE
MANIFEST.in
README.rst
setup.py
pgdf/__init__.py
pgdf/blame.py
pgdf/diff.py
pgdf/git.py
pgdf/main.py
pgdf/summary.py
pgdf.egg-info/PKG-INFO
pgdf.egg-info/SOURCES.txt
pgdf.egg-info/dependency_links.txt
pgdf.egg-info/entry_points.txt
pgdf.egg-info/requires.txt
pgdf.egg-info/top_level.txt