Metadata-Version: 2.1
Name: pgdf
Version: 0.0.1.0
Summary: Tool built with python to summarize git diff into an Excel file.
Author: Kenji Otsuka
Author-email: kok.fdcm@gmail.com
License: MIT
License-File: LICENSE
Requires-Dist: xlsxwriter
